rmkbridge/__init__.py
rmkbridge/__main__.py
rmkbridge/base_handler.py
rmkbridge/config.py
rmkbridge/config.yml
rmkbridge/config_original.yml
rmkbridge/errors.py
rmkbridge/gatling.py
rmkbridge/junit.py
rmkbridge/rmkbridge.py
rmkbridge/rmkbridge_handler_result.py
rmkbridge/robot3_interface.py
rmkbridge/robot4_interface.py
rmkbridge/robot_interface.py
rmkbridge/utils.py
rmkbridge/version.py
rmkbridge/zap.py
robotframework_robotmk_bridge-0.3.1.dist-info/licenses/LICENSE
robotframework_robotmk_bridge-0.3.1.dist-info/METADATA
robotframework_robotmk_bridge-0.3.1.dist-info/WHEEL
robotframework_robotmk_bridge-0.3.1.dist-info/top_level.txt
robotframework_robotmk_bridge-0.3.1.dist-info/RECORD
