Metadata-Version: 2.4
Name: robotframework-robotmk-bridge
Version: 0.3.1
Summary: RobotmkBridge is an extensible tool for Robot Framework that enables you to integrate the results of arbitrary other testing tools into Checkmk. It is based on robotframework-oxygen, written by Eficode Oy, and is designed to facilitate the monitoring of test automation.
Home-page: https://wwww.robotmk.org
Author: Simon Meggle
Author-email: mail@robotmk.org
License: MIT
Keywords: robotframework testing testautomation acceptancetesting atdd bddreporting testreporting robotmk checkmk syntheticmonitoring
Classifier: Development Status :: 5 - Production/Stable
Classifier: Programming Language :: Python :: 3 :: Only
Classifier: Operating System :: OS Independent
Classifier: Topic :: Software Development :: Testing
Classifier: License :: OSI Approved :: MIT License
License-File: LICENSE
Requires-Dist: robotframework<7.0.0,>=6.0.0
Requires-Dist: junitparser==4.0
Requires-Dist: PyYAML>=3.13
Requires-Dist: pydantic>=2.4.2
Dynamic: author
Dynamic: author-email
Dynamic: classifier
Dynamic: description
Dynamic: description-content-type
Dynamic: home-page
Dynamic: keywords
Dynamic: license
Dynamic: license-file
Dynamic: requires-dist
Dynamic: summary
